<openerp>
    <data noupdate="0">
        <!--<record id="dtdream_customer_reception_read" model="ir.rule">-->
            <!--<field name="name">查看客户接待申请</field>-->
            <!--<field name="model_id" ref="model_dtdream_customer_reception"/>-->
            <!--<field name="domain_force">['|',('current_approve.user_id','=', user.id),'|',('name.user_id','=', user.id),'|',('create_uid','=', user.id),'|',('approves.user_id','=',user.id),'|',('accompany_leads.user_id','=',user.id),'|',('interpreter.user_id','=',user.id),'|',('participants.user_id','=',user.id),'|',('showroom_guide.user_id','=',user.id),'|',('car_settings.user_id','=',user.id),('inter_settings.user_id','=',user.id)]</field>-->
            <!--<field name="perm_read" eval="True"/>-->
            <!--<field name="perm_create" eval="False"/>-->
            <!--<field name="perm_write" eval="False"/>-->
            <!--<field name="perm_unlink" eval="False"/>-->
            <!--<field name="groups" eval="[(4, ref('base.group_user'))]"/>-->
        <!--</record>-->

        <!--<record id="dtdream_customer_reception_manage_read" model="ir.rule">-->
            <!--<field name="name">管理员查看所有客户接待申请</field>-->
            <!--<field name="model_id" ref="model_dtdream_customer_reception"/>-->
            <!--<field name="domain_force">[]</field>-->
            <!--<field name="perm_read" eval="True"/>-->
            <!--<field name="perm_create" eval="False"/>-->
            <!--<field name="perm_write" eval="False"/>-->
            <!--<field name="perm_unlink" eval="False"/>-->
            <!--<field name="groups" eval="[(4, ref('customer_reception_manage')),(4, ref('customer_reception_member'))]"/>-->
        <!--</record>-->

    </data>
</openerp>