<?xml version="1.0" encoding="utf-8"?>
<openerp>
    <data>

    <record id="view_model_name_tree" model="ir.ui.view">
        <field name="name">view.model.name.tree</field>
        <field name="model">model.name</field>
        <field name="arch" type="xml">
            <tree>
                <field name="name"/>
            </tree>
        </field>
    </record>

    <record id="view_model_name_form" model="ir.ui.view">
        <field name="name">view.model.name.form</field>
        <field name="model">model.name</field>
        <field name="arch" type="xml">
            <form>
                <sheet>
                    <group>
                        <group>
                            <field name="field_name"/>
                        </group>
                        <group>

                        </group>
                    </group>
                </sheet>
            </form>
        </field>
    </record>



    </data>
</openerp>
